streamlit_ace/__init__.py
streamlit_ace/version.py
streamlit_ace/frontend/build/00292bd41e579436bfe66846683bbba9.js
streamlit_ace/frontend/build/00f32d088488515ac84b1ffe7fc0ec0d.js
streamlit_ace/frontend/build/024358f71f8096dd8052103dced05dbc.js
streamlit_ace/frontend/build/02a3067bd4d8feab048883fbaff9722c.js
streamlit_ace/frontend/build/02fae3ae4ea3a1882c730b75d772670e.js
streamlit_ace/frontend/build/0304e2c71d422d03d4eeec35a6ac97b8.js
streamlit_ace/frontend/build/0403a1b3453a6fbf52be807a7446a7a6.js
streamlit_ace/frontend/build/042b361039b4c32d4ae2c5d10db8e9f5.js
streamlit_ace/frontend/build/049a24dcd51a0ae8fe983447559a9ac0.js
streamlit_ace/frontend/build/0540eebf4f68cfd8b07acd7780c5ed17.js
streamlit_ace/frontend/build/05f6d561bc02454d03d099f367970538.js
streamlit_ace/frontend/build/070adef401d2c781e547079def6be13b.js
streamlit_ace/frontend/build/091c8bd82860a331d15f93d14301c144.js
streamlit_ace/frontend/build/0a5881488d0716c88f53445871de5791.js
streamlit_ace/frontend/build/0a66bba02c732136306a14c928940650.js
streamlit_ace/frontend/build/0a7a9924dc7c660006fffc99dc10b375.js
streamlit_ace/frontend/build/0ad5566a5b5a18d9ba59e3ce2ff02a68.js
streamlit_ace/frontend/build/0b12dd881db5247e85aef081eec1e918.js
streamlit_ace/frontend/build/0b5b72c26d52c3c607ca82660bb82036.js
streamlit_ace/frontend/build/0ba53135e2023ebdf87ee239548b79cc.js
streamlit_ace/frontend/build/0d08ba2776735572e9ac97ffeb59c6e3.js
streamlit_ace/frontend/build/0e1c8d2e18d47ff7c8c1ef5e8c796043.js
streamlit_ace/frontend/build/0e4685ee946f2b5921915053e9bfac42.js
streamlit_ace/frontend/build/0e641de0218eef2ef00ba1b8215c5c68.js
streamlit_ace/frontend/build/0ea873605539240c04717ee939a94fed.js
streamlit_ace/frontend/build/0f2850b53a0fcff39349d8932d4e362a.js
streamlit_ace/frontend/build/0f6a45e5f0fce2b4e74ac6113aa28d45.js
streamlit_ace/frontend/build/0f71a3417cc2258996057f8335f2bfe5.js
streamlit_ace/frontend/build/0fcabfd69c75f69f9c8d532b16e73f38.js
streamlit_ace_clone-0.1.1.dist-info/LICENSE
streamlit_ace_clone-0.1.1.dist-info/METADATA
streamlit_ace_clone-0.1.1.dist-info/WHEEL
streamlit_ace_clone-0.1.1.dist-info/top_level.txt
streamlit_ace_clone-0.1.1.dist-info/RECORD
